byted_overpass_lab_image_text_match_douyin/__init__.py
byted_overpass_lab_image_text_match_douyin-0.0.1.dist-info/METADATA
byted_overpass_lab_image_text_match_douyin-0.0.1.dist-info/WHEEL
byted_overpass_lab_image_text_match_douyin-0.0.1.dist-info/top_level.txt
byted_overpass_lab_image_text_match_douyin-0.0.1.dist-info/RECORD
